cc2dataset/__init__.py
cc2dataset/main.py
cc2dataset/spark_session_builder.py
cc2dataset-1.5.0.data/data/README.md
cc2dataset-1.5.0.dist-info/LICENSE
cc2dataset-1.5.0.dist-info/METADATA
cc2dataset-1.5.0.dist-info/WHEEL
cc2dataset-1.5.0.dist-info/top_level.txt
cc2dataset-1.5.0.dist-info/RECORD
