Metadata-Version: 2.1
Name: cc2dataset
Version: 1.5.0
Summary: Easily convert common crawl to image caption set using pyspark
Home-page: https://github.com/rom1504/cc2dataset
Author: Romain Beaumont
Author-email: romain.rom1@gmail.com
License: MIT
Keywords: machine learning
Platform: UNKNOWN
Classifier: Development Status :: 4 - Beta
Classifier: Intended Audience :: Developers
Classifier: Topic :: Scientific/Engineering :: Artificial Intelligence
Classifier: License :: OSI Approved :: MIT License
Classifier: Programming Language :: Python :: 3.6
Requires-Dist: pyspark
Requires-Dist: pysimdjson
Requires-Dist: fsspec
Requires-Dist: pandas
Requires-Dist: loguru
Requires-Dist: pyarrow
Requires-Dist: fastwarc
Requires-Dist: s3fs
Requires-Dist: fire
Requires-Dist: requests
